soda/cloud/dbt.py
soda/execution/check/dbt_check.py
soda/sodacl/dbt_check_cfg.py
soda_core_dbt-3.5.6.dist-info/LICENSE
soda_core_dbt-3.5.6.dist-info/METADATA
soda_core_dbt-3.5.6.dist-info/WHEEL
soda_core_dbt-3.5.6.dist-info/top_level.txt
soda_core_dbt-3.5.6.dist-info/RECORD
