Metadata-Version: 2.1
Name: soda-core-dbt
Version: 3.5.6
License-File: LICENSE
Requires-Dist: soda-core==3.5.6
Requires-Dist: dbt-core~=1.3.0
